{"classifier":{"classFeatures":{"greetings":{"0":3,"1":3,"2":3},"news":{"0":5,"1":3,"2":4,"19":2,"20":2,"21":2,"22":2},"activity":{"0":3,"1":3},"gross":{"3":2},"insults":{"4":2,"5":3,"6":2,"7":2},"love":{"8":2},"weather":{"9":2,"10":2},"thanks":{"11":3,"22":3,"23":2,"24":3,"25":2},"joke":{"12":2,"13":2,"14":2},"wiki":{"15":2,"16":2,"17":2,"18":2}},"classTotals":{"greetings":5,"news":11,"activity":5,"gross":2,"insults":4,"love":2,"weather":2,"thanks":6,"joke":3,"wiki":2},"totalExamples":33,"smoothing":1},"docs":[{"label":"greetings","text":["hi","hei","hello"]},{"label":"greetings","text":["hi"]},{"label":"greetings","text":["hei"]},{"label":"greetings","text":["hello"]},{"label":"news","text":["hello"]},{"label":"news","text":["hello"]},{"label":"news","text":["hi"]},{"label":"news","text":["hi"]},{"label":"news","text":["hi"]},{"label":"news","text":["hei","hei"]},{"label":"news","text":["hi","hi"]},{"label":"news","text":["hei","hei"]},{"label":"news","text":["hello","hello"]},{"label":"activity","text":["hei"]},{"label":"activity","text":["hei"]},{"label":"activity","text":["hi"]},{"label":"activity","text":["hi"]},{"label":"gross","text":["suck"]},{"label":"insults","text":["shut"]},{"label":"insults","text":["fuck","bitch"]},{"label":"insults","text":["go","fuck"]},{"label":"love","text":["love"]},{"label":"weather","text":["weather","forecast"]},{"label":"thanks","text":["thank","thank"]},{"label":"joke","text":["tell","joke"]},{"label":"joke","text":["laugh"]},{"label":"wiki","text":["defin","search","wiki","wikipedia"]},{"label":"news","text":["Hi","how","are","u"]},{"label":"thanks","text":["Thanks"]},{"label":"thanks","text":["Thank","u"]},{"label":"thanks","text":["Thank","you"]},{"label":"thanks","text":["thank","u"]}],"features":{"hi":9,"hei":8,"hello":6,"suck":1,"shut":1,"fuck":2,"bitch":1,"go":1,"love":1,"weather":1,"forecast":1,"thank":3,"tell":1,"joke":1,"laugh":1,"defin":1,"search":1,"wiki":1,"wikipedia":1,"Hi":1,"how":1,"are":1,"u":3,"Thanks":1,"Thank":2,"you":1},"stemmer":{},"lastAdded":32,"events":{"_events":{},"_eventsCount":0}}